seattle_food_truck/__init__.py
seattle_food_truck/_client.py
seattle_food_truck-0.1.1.data/scripts/sft
seattle_food_truck-0.1.1.dist-info/DESCRIPTION.rst
seattle_food_truck-0.1.1.dist-info/METADATA
seattle_food_truck-0.1.1.dist-info/RECORD
seattle_food_truck-0.1.1.dist-info/WHEEL
seattle_food_truck-0.1.1.dist-info/metadata.json
seattle_food_truck-0.1.1.dist-info/top_level.txt
