Metadata-Version: 2.0
Name: seattle-food-truck
Version: 0.1.1
Summary: UNKNOWN
Home-page: https://github.com/clintval/seattle-food-truck
Author: clintval
Author-email: valentine.clint@gmail.com
License: MIT
Download-URL: https://github.com/clintval/seattle-food-truck/releases/tag/0.1.1
Keywords: seattle,food,truck
Platform: UNKNOWN
Requires-Dist: click
Requires-Dist: python-dateutil
Requires-Dist: requests
Requires-Dist: terminaltables
